stix_shifter_modules/security_advisor/__init__.py
stix_shifter_modules/security_advisor/entry_point.py
stix_shifter_modules/security_advisor/configuration/config.json
stix_shifter_modules/security_advisor/configuration/dialects.json
stix_shifter_modules/security_advisor/configuration/lang_en.json
stix_shifter_modules/security_advisor/stix_translation/__init__.py
stix_shifter_modules/security_advisor/stix_translation/json_to_stix_translator.py
stix_shifter_modules/security_advisor/stix_translation/query_translator.py
stix_shifter_modules/security_advisor/stix_translation/results_translator.py
stix_shifter_modules/security_advisor/stix_translation/json/to_stix_map.json
stix_shifter_modules/security_advisor/stix_transmission/__init__.py
stix_shifter_modules/security_advisor/stix_transmission/auth.py
stix_shifter_modules/security_advisor/stix_transmission/delete_connector.py
stix_shifter_modules/security_advisor/stix_transmission/error_mapper.py
stix_shifter_modules/security_advisor/stix_transmission/ping_connector.py
stix_shifter_modules/security_advisor/stix_transmission/query_connector.py
stix_shifter_modules/security_advisor/stix_transmission/results_connector.py
stix_shifter_modules/security_advisor/stix_transmission/status_connector.py
stix_shifter_modules/security_advisor/stix_transmission/utils/__init__.py
stix_shifter_modules/security_advisor/stix_transmission/utils/sa_findings_api.py
stix_shifter_modules/security_advisor/stix_transmission/utils/sa_occurence_finder.py
stix_shifter_modules/security_advisor/stix_transmission/utils/statement_parser.py
stix_shifter_modules/security_advisor/stix_transmission/utils/stix_pattern_processor.py
stix_shifter_modules_security_advisor-8.0.2.dist-info/licenses/AUTHORS.md
stix_shifter_modules_security_advisor-8.0.2.dist-info/licenses/LICENSE.md
stix_shifter_modules_security_advisor-8.0.2.dist-info/licenses/NOTICE
stix_shifter_modules_security_advisor-8.0.2.dist-info/METADATA
stix_shifter_modules_security_advisor-8.0.2.dist-info/WHEEL
stix_shifter_modules_security_advisor-8.0.2.dist-info/top_level.txt
stix_shifter_modules_security_advisor-8.0.2.dist-info/RECORD
